matchmock/__init__.py
matchmock/py.typed
matchmock-2.1.1.dist-info/LICENSE.txt
matchmock-2.1.1.dist-info/METADATA
matchmock-2.1.1.dist-info/WHEEL
matchmock-2.1.1.dist-info/top_level.txt
matchmock-2.1.1.dist-info/RECORD
