Metadata-Version: 2.1
Name: matchmock
Version: 2.1.1
Summary: Hamcrest matchers for mock objects.
Home-page: https://github.com/keis/matchmock
Author: David Keijser
Author-email: keijser@gmail.com
License-File: LICENSE.txt
Provides-Extra: tests
Requires-Dist: pytest (>=6) ; extra == 'tests'
Requires-Dist: pytest-flakes (>2) ; extra == 'tests'
Requires-Dist: pytest-cov ; extra == 'tests'
Requires-Dist: PyHamcrest ; extra == 'tests'
Requires-Dist: pycodestyle ; extra == 'tests'
Requires-Dist: mock ; extra == 'tests'
Requires-Dist: coveralls ; extra == 'tests'
Requires-Dist: mypy ; extra == 'tests'
Requires-Dist: types-mock ; extra == 'tests'
